{
  "name": "Dev Container",
  "dockerComposeFile": "./compose.yml",
  "service": "devcontainer",
  "shutdownAction": "none",

  "remoteUser": "root",
  "workspaceFolder": "/workspace",

  "mounts": [
    "source=${localEnv:SSH_AUTH_SOCK},target=/ssh-agent,type=bind,consistency=cached"
  ],
  
  "containerEnv": {
    "SSH_AUTH_SOCK": "/ssh-agent"
  },
  
  "postCreateCommand": "bash /root/setup.sh",

  "customizations": {
    "vscode": {
      "extensions": [
        /* monorepo */
        "hashicorp.terraform",
        /* nuxt */
        "nuxtr.nuxt-vscode-extentions",
        "graphql.vscode-graphql",
        "graphql.vscode-graphql-syntax",
        /* general */
        "mskelton.npm-outdated",
        "esbenp.prettier-vscode",
        "cweijan.vscode-database-client2",
        "cweijan.dbclient-jdbc",
        "eamodio.gitlens",
        "formulahendry.auto-rename-tag",
        "wix.vscode-import-cost",
        "gruntfuggly.todo-tree",
        "aaron-bond.better-comments",
        "usernamehw.errorlens"
      ]
    }
  },

  "forwardPorts": [3000, 1337],
  "portsAttributes": {
    "3000": {
      "label": "Nuxt",
      "onAutoForward": "notify"
    },
    "1337": {
      "label": "Strapi",
      "onAutoForward": "notify"
    }
  }
}
